scrape_fast/__init__.py
scrape_fast/browser/__init__.py
scrape_fast/browser/browser.py
scrape_fast/parser/__init__.py
scrape_fast/parser/parse.py
scrape_fast/proxies/__init__.py
scrape_fast/proxies/proxy_list.py
scrape_fast/simple/__init__.py
scrape_fast/simple/http.py
scrape_fast-0.101.dist-info/License.txt
scrape_fast-0.101.dist-info/METADATA
scrape_fast-0.101.dist-info/WHEEL
scrape_fast-0.101.dist-info/top_level.txt
scrape_fast-0.101.dist-info/RECORD
